CHANGELOG.md
MANIFEST.in
README.md
setup.py
queue_util/__init__.py
queue_util/consumer.py
queue_util/producer.py
queue_util/serializers.py
queue_util/stats.py
queue_util.egg-info/PKG-INFO
queue_util.egg-info/SOURCES.txt
queue_util.egg-info/dependency_links.txt
queue_util.egg-info/requires.txt
queue_util.egg-info/top_level.txt
tests/__init__.py
tests/integration/__init__.py
tests/integration/app.py
tests/integration/run_tests.py
tests/unit/__init__.py
tests/unit/test_consumer.py